configchecker/__init__.py
configchecker-1.0.1.dist-info/LICENSE
configchecker-1.0.1.dist-info/METADATA
configchecker-1.0.1.dist-info/WHEEL
configchecker-1.0.1.dist-info/top_level.txt
configchecker-1.0.1.dist-info/RECORD
