Metadata-Version: 2.1
Name: configchecker
Version: 1.0.1
Summary: INI-config validator
Home-page: https://github.com/victorsamun/configvalidator
Download-URL: https://github.com/victorsamun/configvalidator/archive/master.zip
Author: Samun Victor
Author-email: victor.samun@gmail.com
License: MIT
Keywords: configparser configchecker checking validate
Classifier: Development Status :: 5 - Production/Stable
Classifier: License :: OSI Approved :: MIT License
Classifier: Programming Language :: Python :: 3 :: Only
Classifier: Programming Language :: Python :: 3.4
Classifier: Programming Language :: Python :: 3.5
Classifier: Programming Language :: Python :: 3.6
Classifier: Programming Language :: Python :: 3.7
Classifier: Programming Language :: Python :: 3.8
Classifier: Programming Language :: Python :: 3.9
Classifier: Programming Language :: Python :: 3.10
Classifier: Programming Language :: Python :: 3.11
Classifier: Programming Language :: Python :: 3.12
License-File: LICENSE
